perform/__init__.py
perform/admin.py
perform/apps.py
perform/forms.py
perform/models.py
perform/signals.py
perform/tests.py
perform/urls.py
perform/utils.py
perform/views.py
perform/migrations/0001_initial.py
perform/migrations/0002_evalchoiceplanning_evalplanning.py
perform/migrations/0003_evalplanninga_evalplanningb.py
perform/migrations/0004_evalplanninga_eval_date.py
perform/migrations/0005_evalplanninga_enter_date.py
perform/migrations/0006_evalplanninga_usereval.py
perform/migrations/0007_auto_20230217_0014.py
perform/migrations/0008_evalpreassessment_evalpreassessmenta_evalpreassessmentb.py
perform/migrations/0009_auto_20230217_1813.py
perform/migrations/0010_auto_20230217_2302.py
perform/migrations/0011_evalplanning_date.py
perform/migrations/0012_auto_20230218_1538.py
perform/migrations/0013_auto_20230218_1557.py
perform/migrations/0014_auto_20230218_1645.py
perform/migrations/0015_rename_eval_obj_date_evalpreassessment_eval_beh_date.py
perform/migrations/0016_auto_20230218_1718.py
perform/migrations/0017_auto_20230218_1719.py
perform/migrations/0018_auto_20230218_1827.py
perform/migrations/0019_auto_20230307_0950.py
perform/migrations/0020_auto_20230307_1026.py
perform/migrations/0021_auto_20230307_1027.py
perform/migrations/0022_auto_20230310_0923.py
perform/migrations/0023_rename_year_evalmonth_month.py
perform/migrations/0024_remove_evaltype_month.py
perform/migrations/0025_evalplanning_month.py
perform/migrations/__init__.py
perform/migrations/__pycache__/0001_initial.cpython-310.pyc
perform/migrations/__pycache__/0002_evalchoiceplanning_evalplanning.cpython-310.pyc
perform/migrations/__pycache__/0003_evalplanninga_evalplanningb.cpython-310.pyc
perform/migrations/__pycache__/0004_evalplanninga_eval_date.cpython-310.pyc
perform/migrations/__pycache__/0005_evalplanninga_enter_date.cpython-310.pyc
perform/migrations/__pycache__/0006_evalplanninga_usereval.cpython-310.pyc
perform/migrations/__pycache__/0007_auto_20230217_0014.cpython-310.pyc
django_ipghrms_perform-1.1.dist-info/LICENSE
django_ipghrms_perform-1.1.dist-info/METADATA
django_ipghrms_perform-1.1.dist-info/WHEEL
django_ipghrms_perform-1.1.dist-info/top_level.txt
django_ipghrms_perform-1.1.dist-info/RECORD
